simplelatexocr/__init__.py
simplelatexocr/get_lastest_model.py
simplelatexocr/main.py
simplelatexocr/models.py
simplelatexocr/utils.py
simplelatexocr/utils_load.py
simplelatexocr/api/__init__.py
simplelatexocr/api/app.py
simplelatexocr/api/run.py
simplelatexocr/api/streamlit.py
simplelatexocr-0.0.4.dist-info/LICENSE
simplelatexocr-0.0.4.dist-info/METADATA
simplelatexocr-0.0.4.dist-info/WHEEL
simplelatexocr-0.0.4.dist-info/top_level.txt
simplelatexocr-0.0.4.dist-info/RECORD
