Metadata-Version: 2.1
Name: simplelatexocr
Version: 0.0.4
Summary: A simple LaTeX OCR package
Author: chaodreaming
Author-email: chaodreaming@gmail.com
License: Apache-2.0
Classifier: Development Status :: 3 - Alpha
Classifier: Intended Audience :: Developers
Classifier: License :: OSI Approved :: Apache Software License
Classifier: Programming Language :: Python :: 3.8
Classifier: Programming Language :: Python :: 3.9
Classifier: Programming Language :: Python :: 3.10
Classifier: Programming Language :: Python :: 3.11
Requires-Python: >=3.8
License-File: LICENSE
Requires-Dist: onnxruntime-gpu
Requires-Dist: tokenizers >=0.13.2
Requires-Dist: numpy
Requires-Dist: opencv-python
Requires-Dist: Pillow >=9.2.0
Requires-Dist: PyYAML
Requires-Dist: transformers
Requires-Dist: flask
Requires-Dist: fastapi
Requires-Dist: uvicorn
Requires-Dist: opencv-python-headless
